reflex_lottiefiles/__init__.py
reflex_lottiefiles/lottiefiles.py
reflex_lottiefiles-0.0.2.dist-info/LICENSE
reflex_lottiefiles-0.0.2.dist-info/METADATA
reflex_lottiefiles-0.0.2.dist-info/WHEEL
reflex_lottiefiles-0.0.2.dist-info/top_level.txt
reflex_lottiefiles-0.0.2.dist-info/RECORD
