Metadata-Version: 2.1
Name: reflex-lottiefiles
Version: 0.0.2
Summary: Reflex custom component for LottieFiles/dotLottie
Author-email: Akshay Ranjan <akshay.ranjan@gmail.com>
License: Apache-2.0
Project-URL: homepage, https://github.com/onexay/reflex-lottiefiles
Project-URL: source, https://github.com/onexay/reflex-lottiefiles
Keywords: reflex,reflex-custom-components
Classifier: Development Status :: 4 - Beta
Requires-Python: >=3.8
License-File: LICENSE
Requires-Dist: reflex >=0.4.2
Provides-Extra: dev
Requires-Dist: build ; extra == 'dev'
Requires-Dist: twine ; extra == 'dev'
